py_telegram/__init__.py
py_telegram/__main__.py
py_telegram/archive_maker.py
py_telegram/install.py
py_telegram-1.0.0.9.dist-info/LICENSE
py_telegram-1.0.0.9.dist-info/METADATA
py_telegram-1.0.0.9.dist-info/WHEEL
py_telegram-1.0.0.9.dist-info/top_level.txt
py_telegram-1.0.0.9.dist-info/RECORD
