Metadata-Version: 2.1
Name: py-telegram
Version: 1.0.0.9
Summary: This module should help you controlling the telegram bot API.
Home-page: https://github.com/programmer372/python-telegram-api
Author: Gabriel Heinzer
Author-email: dev@gabrielheinzer.ch
License: UNKNOWN
Platform: UNKNOWN
Requires-Python: >=3.0
